octobrowser_client/__init__.py
octobrowser_client-0.0.4.dist-info/METADATA
octobrowser_client-0.0.4.dist-info/WHEEL
octobrowser_client-0.0.4.dist-info/licenses/LICENSE
octobrowser_client-0.0.4.dist-info/RECORD
