Metadata-Version: 2.4
Name: octobrowser-client
Version: 0.0.4
Summary: Octobrowser api client
License-File: LICENSE
Requires-Python: >=3.12
Requires-Dist: httpx>=0.28.1
